{
	"rtn_tip": "",
	"rtn_msg": "",
	"rtn_ftype": "0",
	"rtn_ext": "",
	"data": {
		"productList": [{
			"imageUrl": "https://m.360buyimg.com/mobilecms/s450x450_jfs/t5719/115/7116346600/113182/33686e76/596ea898N45e022d0.jpg",
			"jdPrice": 120.00,
			"weightPosition": 60015,
			"type": 0,
			"endTime": 1539835199000,
			"startTime": 1539748800000,
			"id": 45992631,
			"categoryId3": 13555,
			"categoryId1": 12218,
			"categoryId2": 12221,
			"name": "澳大利亚进口脐橙 丑橙 4kg装 新鲜水果",
			"skuId": 5297628,
			"rebate": 10.0,
			"isTop": 0,
			"peopleUpper": 4000,
			"siteType": 1,
			"status": 20,
			"spuId": 1599930,
			"soldRate": 39,
			"skuOrder": -56,
			"price": 49.80,
			"linkUrlApp": "yhd://onesnapup?body={\"topqianggouId\":\"45992631\"}",
			"isSpecialKill": 0
		}, {
			"imageUrl": "https://m.360buyimg.com/mobilecms/s450x450_jfs/t21187/44/2658482691/244694/1f9cf16c/5b5e819bN80c8511e.jpg",
			"jdPrice": 40.00,
			"weightPosition": 8362,
			"type": 0,
			"endTime": 1539835199000,
			"startTime": 1539748800000,
			"id": 46076856,
			"categoryId3": 2675,
			"categoryId1": 1320,
			"categoryId2": 1584,
			"name": "金龙鱼 东北米 粳米 寒地东北大米 5kg  （新老包装随机发放）",
			"skuId": 2205070,
			"rebate": 10.0,
			"isTop": 0,
			"peopleUpper": 6000,
			"siteType": 1,
			"status": 20,
			"spuId": 2205070,
			"soldRate": 55,
			"skuOrder": -75,
			"price": 26.80,
			"linkUrlApp": "yhd://onesnapup?body={\"topqianggouId\":\"46076856\"}",
			"isSpecialKill": 0
		}, {
			"imageUrl": "https://m.360buyimg.com/n12/s450x450_jfs/t20791/119/2019391714/283574/1b79da38/5b4415b0N39d92810.jpg",
			"jdPrice": 265.00,
			"weightPosition": 8362,
			"type": 0,
			"endTime": 1539763200000,
			"startTime": 1539748800000,
			"id": 45780825,
			"categoryId3": 12215,
			"categoryId1": 1320,
			"categoryId2": 5019,
			"name": "德国原装进口牛奶 德亚（Weidendorf）脱脂纯牛奶 1L*12盒 整箱装",
			"skuId": 896023,
			"rebate": 0.9,
			"isTop": 0,
			"peopleUpper": 3000,
			"siteType": 1,
			"status": 20,
			"soldRate": 8,
			"skuOrder": -41,
			"price": 109.00,
			"linkUrlApp": "yhd://onesnapup?body={\"topqianggouId\":\"45780825\"}",
			"isSpecialKill": 0
		}, {
			"imageUrl": "https://m.360buyimg.com/n12/s450x450_jfs/t20080/170/423088570/220983/58eb70e3/5af3d94aNf6f4407e.jpg",
			"jdPrice": 109.60,
			"weightPosition": 8362,
			"type": 0,
			"endTime": 1539763200000,
			"startTime": 1539748800000,
			"id": 45744281,
			"categoryId3": 3986,
			"categoryId1": 1320,
			"categoryId2": 1585,
			"name": "麦斯威尔原味速溶咖啡13g*100条袋装（新老包装交替发货）",
			"skuId": 1953169,
			"rebate": 0.7,
			"isTop": 0,
			"peopleUpper": 2000,
			"siteType": 1,
			"status": 20,
			"soldRate": 0,
			"skuOrder": -41,
			"price": 69.90,
			"linkUrlApp": "yhd://onesnapup?body={\"topqianggouId\":\"45744281\"}",
			"isSpecialKill": 0
		}, {
			"imageUrl": "https://m.360buyimg.com/mobilecms/s450x450_jfs/t2800/16/1394624793/436160/25caec0c/573ecb0bNd8ca3039.jpg",
			"jdPrice": 199.00,
			"weightPosition": 8361,
			"type": 0,
			"endTime": 1539835199000,
			"startTime": 1539748800000,
			"id": 46119059,
			"categoryId3": 12215,
			"categoryId1": 1320,
			"categoryId2": 5019,
			"name": "荷兰原装进口 荷高（Globemilk） 脱脂纯牛奶1L*6整箱装 3.7%乳蛋白",
			"skuId": 2858180,
			"rebate": 10.0,
			"isTop": 0,
			"peopleUpper": 5000,
			"siteType": 1,
			"status": 20,
			"spuId": 2858180,
			"soldRate": 36,
			"skuOrder": -54,
			"price": 59.00,
			"linkUrlApp": "yhd://onesnapup?body={\"topqianggouId\":\"46119059\"}",
			"isSpecialKill": 0
		}, {
			"imageUrl": "https://m.360buyimg.com/mobilecms/s450x450_jfs/t27358/38/959885588/178223/2fc2bd01/5bbdeaf7N98a5ea45.jpg",
			"jdPrice": 518.00,
			"weightPosition": 8361,
			"type": 0,
			"endTime": 1539835199000,
			"startTime": 1539748800000,
			"id": 45525073,
			"categoryId3": 1396,
			"categoryId1": 1316,
			"categoryId2": 1381,
			"name": "珀莱雅水漾芯肌唱享水润化妆品套装 补水保湿护肤品礼盒 （洁水乳+喷雾+睡眠面膜+海藻面膜3片+旅行装）",
			"skuId": 2286059,
			"rebate": 10.0,
			"isTop": 0,
			"peopleUpper": 1500,
			"siteType": 1,
			"status": 20,
			"spuId": 7475065,
			"soldRate": 18,
			"skuOrder": -31,
			"price": 219.00,
			"linkUrlApp": "yhd://onesnapup?body={\"topqianggouId\":\"45525073\"}",
			"isSpecialKill": 0
		}, {
			"imageUrl": "https://m.360buyimg.com/mobilecms/s450x450_jfs/t19318/298/828596222/118525/a9c4d268/5aaa048aN81ca1ffb.jpg",
			"jdPrice": 140.10,
			"weightPosition": 8360,
			"type": 0,
			"endTime": 1539835199000,
			"startTime": 1539748800000,
			"id": 45748218,
			"categoryId3": 7052,
			"categoryId1": 1319,
			"categoryId2": 1523,
			"name": "伊利奶粉 沛能系列（原金装） 幼儿配方奶粉 3段1200克超值三联包新包装（1-3岁幼儿适用）新老包装随机发货",
			"skuId": 1139014,
			"rebate": 10.0,
			"isTop": 0,
			"peopleUpper": 1000,
			"siteType": 1,
			"status": 20,
			"spuId": 1139014,
			"soldRate": 48,
			"skuOrder": -54,
			"price": 91.00,
			"linkUrlApp": "yhd://onesnapup?body={\"topqianggouId\":\"45748218\"}",
			"isSpecialKill": 0
		}, {
			"imageUrl": "https://m.360buyimg.com/mobilecms/s450x450_jfs/t9922/82/1780596905/1059082/32be876f/59e5b42aN4d82176a.jpg",
			"jdPrice": 159.00,
			"weightPosition": 8360,
			"type": 0,
			"endTime": 1539835199000,
			"startTime": 1539748800000,
			"id": 45745711,
			"categoryId3": 15908,
			"categoryId1": 15901,
			"categoryId2": 15902,
			"name": "泉林本色 抽纸 不漂白本色纸面巾纸巾200抽*15包（整箱销售）",
			"skuId": 1547661,
			"rebate": 10.0,
			"isTop": 0,
			"peopleUpper": 4000,
			"siteType": 1,
			"status": 20,
			"spuId": 3723618,
			"soldRate": 37,
			"skuOrder": -52,
			"price": 58.80,
			"linkUrlApp": "yhd://onesnapup?body={\"topqianggouId\":\"45745711\"}",
			"isSpecialKill": 0
		}, {
			"imageUrl": "https://m.360buyimg.com/mobilecms/s450x450_jfs/t4459/338/3533509767/48771/6acaec1c/58feb1b1N2fa79ce1.jpg",
			"jdPrice": 1880.00,
			"weightPosition": 8360,
			"type": 0,
			"endTime": 1539835199000,
			"startTime": 1539748800000,
			"id": 45750077,
			"categoryId3": 1550,
			"categoryId1": 1319,
			"categoryId2": 1526,
			"name": "美德乐（Medela）瑞士进口丝韵单侧电动吸奶器孕产妇大吸力超静音泌乳拔奶器",
			"skuId": 1290975,
			"rebate": 0.8,
			"isTop": 0,
			"peopleUpper": 1000,
			"siteType": 1,
			"status": 20,
			"spuId": 1290975,
			"soldRate": 30,
			"skuOrder": -49,
			"price": 1096.00,
			"linkUrlApp": "yhd://onesnapup?body={\"topqianggouId\":\"45750077\"}",
			"isSpecialKill": 0
		}, {
			"imageUrl": "https://m.360buyimg.com/mobilecms/s450x450_jfs/t16843/284/1828824929/237437/4818e371/5ad99abcN758f046c.jpg",
			"jdPrice": 298.00,
			"weightPosition": 8360,
			"type": 0,
			"endTime": 1539835199000,
			"startTime": 1539748800000,
			"id": 45516330,
			"categoryId3": 1537,
			"categoryId1": 1319,
			"categoryId2": 1524,
			"name": "合生元（BIOSTIME）儿童益生菌冲剂(益生元)原味48袋装（0-7岁宝宝婴幼儿  法国进口活性益生菌）",
			"skuId": 1178664,
			"rebate": 10.0,
			"isTop": 0,
			"peopleUpper": 600,
			"siteType": 1,
			"status": 20,
			"spuId": 1178676,
			"soldRate": 40,
			"skuOrder": -43,
			"price": 266.00,
			"linkUrlApp": "yhd://onesnapup?body={\"topqianggouId\":\"45516330\"}",
			"isSpecialKill": 0
		}, {
			"imageUrl": "https://m.360buyimg.com/n12/s450x450_jfs/t23644/36/864460134/614615/e291a872/5b471a5dN7e2639f4.jpg",
			"jdPrice": 1200.00,
			"weightPosition": 8360,
			"type": 0,
			"endTime": 1539835199000,
			"startTime": 1539748800000,
			"id": 45930481,
			"categoryId3": 12205,
			"categoryId1": 1320,
			"categoryId2": 12202,
			"name": "2018新茶 盛茗世家茶叶 西湖龙井茶明前特级250g 凝绿礼盒装 春茶绿茶",
			"skuId": 5895362,
			"rebate": 0.9,
			"isTop": 0,
			"peopleUpper": 100,
			"siteType": 1,
			"status": 20,
			"soldRate": 0,
			"skuOrder": -33,
			"price": 468.00,
			"linkUrlApp": "yhd://onesnapup?body={\"topqianggouId\":\"45930481\"}",
			"isSpecialKill": 0
		}, {
			"imageUrl": "https://m.360buyimg.com/mobilecms/s450x450_jfs/t26518/337/954373457/203931/1be6bcd4/5bbd99f8Ndb466701.jpg",
			"jdPrice": 1059.00,
			"weightPosition": 8360,
			"type": 0,
			"endTime": 1539835199000,
			"startTime": 1539748800000,
			"id": 45366160,
			"categoryId3": 15258,
			"categoryId1": 15248,
			"categoryId2": 15249,
			"name": "恒源祥 新疆棉被芯 全棉棉花被秋冬棉被子 床上用品 棉花被 200*230cm（总重6斤净重4.2斤）",
			"skuId": 5463457,
			"rebate": 10.0,
			"isTop": 0,
			"peopleUpper": 450,
			"siteType": 1,
			"status": 20,
			"spuId": 5039079,
			"soldRate": 22,
			"skuOrder": -27,
			"price": 269.00,
			"linkUrlApp": "yhd://onesnapup?body={\"topqianggouId\":\"45366160\"}",
			"isSpecialKill": 0
		}, {
			"imageUrl": "https://m.360buyimg.com/mobilecms/s450x450_jfs/t20305/131/2317843517/125101/29ff5597/5b503771N06e4e652.jpg",
			"jdPrice": 9999.00,
			"weightPosition": 8360,
			"type": 0,
			"endTime": 1539835199000,
			"startTime": 1539748800000,
			"id": 45363516,
			"categoryId3": 672,
			"categoryId1": 670,
			"categoryId2": 671,
			"name": "荣耀MagicBook 14英寸轻薄窄边框笔记本电脑（i5-8250U 8G 256G Intel FHD IPS 正版Office）冰河银",
			"skuId": 8461531,
			"rebate": 10.0,
			"isTop": 0,
			"peopleUpper": 300,
			"siteType": 1,
			"status": 20,
			"spuId": 8461531,
			"soldRate": 24,
			"skuOrder": -26,
			"price": 4788.00,
			"linkUrlApp": "yhd://onesnapup?body={\"topqianggouId\":\"45363516\"}",
			"isSpecialKill": 0
		}, {
			"imageUrl": "https://m.360buyimg.com/mobilecms/s450x450_jfs/t1/5849/19/2729/107447/5b975eb0Ec615051e/eeb34950512bdada.jpg",
			"jdPrice": 45.00,
			"weightPosition": 60015,
			"type": 0,
			"endTime": 1539827999000,
			"startTime": 1539741600000,
			"id": 45929611,
			"categoryId3": 1594,
			"categoryId1": 1320,
			"categoryId2": 1583,
			"name": "士力架 花生夹心巧克力（全家桶）糖果 巧克力 休闲零食 460g",
			"skuId": 326467,
			"rebate": 0.8,
			"isTop": 0,
			"peopleUpper": 20000,
			"siteType": 1,
			"status": 20,
			"spuId": 326467,
			"soldRate": 79,
			"skuOrder": -119,
			"price": 29.50,
			"linkUrlApp": "yhd://onesnapup?body={\"topqianggouId\":\"45929611\"}",
			"isSpecialKill": 0
		}, {
			"imageUrl": "https://m.360buyimg.com/mobilecms/s450x450_jfs/t22150/65/410734592/90036/2f5508f/5b0cc4eaN08875947.jpg",
			"jdPrice": 113.90,
			"weightPosition": 60015,
			"type": 0,
			"endTime": 1539827999000,
			"startTime": 1539741600000,
			"id": 45860004,
			"categoryId3": 15927,
			"categoryId1": 15901,
			"categoryId2": 15904,
			"name": "金纺 衣物护理剂 怡神薰衣草 2.5L+2.5L(柔顺剂)",
			"skuId": 3895219,
			"rebate": 10.0,
			"isTop": 0,
			"peopleUpper": 5000,
			"siteType": 1,
			"status": 20,
			"spuId": 3895219,
			"soldRate": 78,
			"skuOrder": -92,
			"price": 52.80,
			"linkUrlApp": "yhd://onesnapup?body={\"topqianggouId\":\"45860004\"}",
			"isSpecialKill": 0
		}],
		"nextHourbuyTime": {
			"sellPointStartColor": "#f73737",
			"sellPointEndColor": "#f97728",
			"endTime": 1539763200000,
			"activityTime": 1539756000000,
			"sellPointTitle": "爆款超值购"
		},
		"hourbuyTime": {
			"sellPointStartColor": "#f73737",
			"sellPointEndColor": "#f97728",
			"endTime": 1539756000000,
			"activityTime": 1539748800000,
			"sellPointTitle": "爆款超值购"
		}
	},
	"rtn_code": "0",
	"clientIp": "61.144.96.74"
}